iphreeqc.py
test_iphreeqc/__init__.py
test_iphreeqc/test_ex2.py
test_iphreeqc/test_ex3.py
test_iphreeqc/test_ex4.py
test_iphreeqc/test_ex5.py
test_iphreeqc/test_ex6.py
test_iphreeqc/test_ex7.py
test_iphreeqc/examples/Zn1e_4
test_iphreeqc/examples/Zn1e_7
test_iphreeqc/examples/co2.tsv
test_iphreeqc/examples/ex1
test_iphreeqc/examples/ex10
test_iphreeqc/examples/ex11
test_iphreeqc/examples/ex12
test_iphreeqc/examples/ex12a
test_iphreeqc/examples/ex13a
test_iphreeqc/examples/ex13ac
test_iphreeqc/examples/ex13b
test_iphreeqc/examples/ex13c
test_iphreeqc/examples/ex14
test_iphreeqc/examples/ex15
test_iphreeqc/examples/ex15.dat
test_iphreeqc/examples/ex15a
test_iphreeqc/examples/ex15b
test_iphreeqc/examples/ex16
test_iphreeqc/examples/ex17
test_iphreeqc/examples/ex17b
test_iphreeqc/examples/ex18
test_iphreeqc/examples/ex19
test_iphreeqc/examples/ex19_meas.tsv
test_iphreeqc/examples/ex19b
test_iphreeqc/examples/ex2
test_iphreeqc/examples/ex20-c13.tsv
test_iphreeqc/examples/ex20-c14.tsv
test_iphreeqc/examples/ex20a
test_iphreeqc/examples/ex20b
test_iphreeqc/examples/ex21
test_iphreeqc/examples/ex21_Cl_tr_rad.tsv
test_iphreeqc/examples/ex21_Cs_rad.tsv
test_iphreeqc/examples/ex21_HTO_rad.tsv
test_iphreeqc/examples/ex21_Na_tr_rad.tsv
test_iphreeqc/examples/ex22
test_iphreeqc/examples/ex2b
test_iphreeqc/examples/ex2b.tsv
test_iphreeqc/examples/ex3
test_iphreeqc/examples/ex4
test_iphreeqc/examples/ex5
test_iphreeqc/examples/ex6
test_iphreeqc/examples/ex7
test_iphreeqc/examples/ex8
test_iphreeqc/examples/ex9
iphreeqc_py-0.3.1.dist-info/COPYING
iphreeqc_py-0.3.1.dist-info/COPYING.LESSER
iphreeqc_py-0.3.1.dist-info/METADATA
iphreeqc_py-0.3.1.dist-info/WHEEL
iphreeqc_py-0.3.1.dist-info/top_level.txt
iphreeqc_py-0.3.1.dist-info/RECORD
