Metadata-Version: 2.1
Name: iphreeqc-py
Version: 0.3.1
Summary: python 3+ ctypes wrapper for selected function prototypes defined by IPhreeqc version 3 in IPhreeqc.h and Var.h
Home-page: https://github.com/stuart-nolan/iphreeqc-py.git
Author: Stuart Nolan
Author-email: 61199416+stuart-nolan@users.noreply.github.com
License: UNKNOWN
Platform: UNKNOWN
Classifier: Programming Language :: Python :: 3
Classifier: License :: OSI Approved :: GNU Lesser General Public License v3 (LGPLv3)
Classifier: Operating System :: POSIX :: Linux
License-File: COPYING
License-File: COPYING.LESSER
